bayesvalidrox/__init__.py
bayesvalidrox/bayesvalidrox.mplstyle
bayesvalidrox/bayes_inference/__init__.py
bayesvalidrox/bayes_inference/bayes_inference.py
bayesvalidrox/bayes_inference/bayes_model_comparison.py
bayesvalidrox/bayes_inference/discrepancy.py
bayesvalidrox/bayes_inference/mcmc.py
bayesvalidrox/bayes_inference/post_sampler.py
bayesvalidrox/bayes_inference/rejection_sampler.py
bayesvalidrox/post_processing/__init__.py
bayesvalidrox/post_processing/post_processing.py
bayesvalidrox/pylink/__init__.py
bayesvalidrox/pylink/pylink.py
bayesvalidrox/surrogate_models/__init__.py
bayesvalidrox/surrogate_models/apoly_construction.py
bayesvalidrox/surrogate_models/bayes_linear.py
bayesvalidrox/surrogate_models/engine.py
bayesvalidrox/surrogate_models/eval_rec_rule.py
bayesvalidrox/surrogate_models/exp_designs.py
bayesvalidrox/surrogate_models/exploration.py
bayesvalidrox/surrogate_models/gaussian_process_sklearn.py
bayesvalidrox/surrogate_models/glexindex.py
bayesvalidrox/surrogate_models/input_space.py
bayesvalidrox/surrogate_models/inputs.py
bayesvalidrox/surrogate_models/meta_model.py
bayesvalidrox/surrogate_models/orthogonal_matching_pursuit.py
bayesvalidrox/surrogate_models/pce_gpr.py
bayesvalidrox/surrogate_models/polynomial_chaos.py
bayesvalidrox/surrogate_models/reg_fast_ard.py
bayesvalidrox/surrogate_models/reg_fast_laplace.py
bayesvalidrox/surrogate_models/sequential_design.py
bayesvalidrox/surrogate_models/supplementary.py
bayesvalidrox-2.1.0.dist-info/licenses/LICENCE.md
bayesvalidrox-2.1.0.dist-info/METADATA
bayesvalidrox-2.1.0.dist-info/WHEEL
bayesvalidrox-2.1.0.dist-info/top_level.txt
bayesvalidrox-2.1.0.dist-info/RECORD
