Metadata-Version: 2.4
Name: bayesvalidrox
Version: 2.1.0
Summary: An open-source, object-oriented Python package for surrogate-assisted Bayesain Validation of computational models.
Home-page: https://git.iws.uni-stuttgart.de/inversemodeling/bayesian-validation
Author: Farid Mohammadi, Rebecca Kohlhaas
Author-email: farid.mohammadi@iws.uni-stuttgart.de, rebecca.kohlhaas@iws.uni-stuttgart.de
Classifier: Programming Language :: Python :: 3
Classifier: Operating System :: OS Independent
Requires-Python: >=3.8
License-File: LICENCE.md
Requires-Dist: numpy>=1.23.5
Requires-Dist: pandas==1.4.4
Requires-Dist: joblib==1.1.1
Requires-Dist: matplotlib==3.7.3
Requires-Dist: seaborn==0.11.1
Requires-Dist: scipy>=1.11.1
Requires-Dist: scikit-learn==1.3.1
Requires-Dist: tqdm>=4.61.1
Requires-Dist: chaospy==4.3.3
Requires-Dist: emcee==3.0.2
Requires-Dist: corner==2.2.1
Requires-Dist: h5py==3.9.0
Requires-Dist: statsmodels==0.14.2
Requires-Dist: multiprocess==0.70.16
Requires-Dist: datasets==2.20.0
Requires-Dist: umbridge==1.2.4
Dynamic: license-file
